pymcpevals/__init__.py
pymcpevals/cli.py
pymcpevals/config.py
pymcpevals/core.py
pymcpevals/py.typed
pymcpevals/pytest_plugin.py
pymcpevals/types.py
pymcpevals/yaml_config.py
pymcpevals-0.1.1.dist-info/licenses/LICENSE
pymcpevals-0.1.1.dist-info/METADATA
pymcpevals-0.1.1.dist-info/WHEEL
pymcpevals-0.1.1.dist-info/entry_points.txt
pymcpevals-0.1.1.dist-info/top_level.txt
pymcpevals-0.1.1.dist-info/RECORD
