Metadata-Version: 2.4
Name: pymcpevals
Version: 0.1.1
Summary: Python package for evaluating MCP (Model Context Protocol) server implementations using LLM-based scoring
Author-email: Akshay Ram Vignesh <akshay5995@gmail.com>
License: MIT
Project-URL: Homepage, https://github.com/akshay5995/pymcpevals
Project-URL: Documentation, https://github.com/akshay5995/pymcpevals#readme
Project-URL: Repository, https://github.com/akshay5995/pymcpevals
Project-URL: Issues, https://github.com/akshay5995/pymcpevals/issues
Keywords: mcp,evaluation,testing,llm,ai
Classifier: Development Status :: 3 - Alpha
Classifier: Intended Audience :: Developers
Classifier: Programming Language :: Python :: 3
Classifier: Programming Language :: Python :: 3.10
Classifier: Programming Language :: Python :: 3.11
Classifier: Programming Language :: Python :: 3.12
Classifier: Framework :: Pytest
Classifier: Topic :: Software Development :: Testing
Requires-Python: >=3.10
License-File: LICENSE
Requires-Dist: fastmcp>=0.5.0
Requires-Dist: litellm>=1.0.0
Requires-Dist: pydantic>=2.0.0
Requires-Dist: pyyaml>=6.0
Requires-Dist: click>=8.0.0
Requires-Dist: rich>=13.0.0
Provides-Extra: dev
Requires-Dist: pytest>=7.0.0; extra == "dev"
Requires-Dist: pytest-cov>=4.0.0; extra == "dev"
Requires-Dist: pytest-asyncio>=0.21.0; extra == "dev"
Requires-Dist: black>=23.0.0; extra == "dev"
Requires-Dist: ruff>=0.0.270; extra == "dev"
Requires-Dist: mypy>=1.0.0; extra == "dev"
Requires-Dist: types-pyyaml; extra == "dev"
Provides-Extra: pytest
Requires-Dist: pytest>=7.0.0; extra == "pytest"
Requires-Dist: pytest-asyncio>=0.21.0; extra == "pytest"
Dynamic: license-file
